Workbook

Sheet BOM
A1: Item | B1: Part | C1: Spec to order | D1: Make / Buy | E1: Qty per kit | F1: Unit cost ₹ (prototype) | G1: Line cost ₹ | H1: Price basis | I1: Supplier candidates
A2: 1 | B2: Lid with fill chute and window | C2: 304 lid Ø168 × 0.8–1.2 pressed or spun, Ø16 chute, funnel, Ø20 glass window | D2: Make | E2: 1 | F2: 2500 | G2: =E2*F2 -> 2500 | H2: Estimate, one-off fabrication | I2: SS fabricators, Peenya / Jigani (Bangalore)
A3: 2 | B3: Lid interlock + lock | C3: 12 mm reed switch + magnet; 24 V mini push solenoid | D3: Buy | E3: 1 | F3: 420 | G3: =E3*F3 -> 420 | H3: Reed ₹28 (Robocraze) + magnet + solenoid estimate | I3: Robocraze; Robu; local electronics
A4: 3 | B4: Bowl, spout and flow pins | C4: 304 sheet 0.8 mm rolled Ø150 × 226, welded floor, boss for the seal, Ø10 spout, 2 × 316 Ø1.6 pins | D4: Make | E4: 1 | F4: 3000 | G4: =E4*F4 -> 3000 | H4: Estimate, one-off fabrication | I4: SS fabricators, Peenya / Jigani
A5: 4 | B5: Sleeve clamp ring | C5: 316 Ø66 × 4, ID 52, knurled | D5: Make | E5: 1 | F5: 900 | G5: =E5*F5 -> 900 | H5: Estimate, CNC one-off | I5: CNC job shops, Peenya
A6: 5 | B6: Sleeve O-ring | C6: Silicone 51 × 1.6, food grade (from a kit) | D6: Buy | E6: 1 | F6: 60 | G6: =E6*F6 -> 60 | H6: Share of a ₹600 silicone O-ring kit | I6: Cart2India / IndiaMART O-ring kits
A7: 6 | B7: Filter sleeve, two layers (consumable) | C7: Whatman 602 h, 240 mm circles (cat. 10312620): 4 per sleeve | D7: Buy | E7: 1 | F7: =Assumptions!B4*Assumptions!B2*(1+Assumptions!B3)/100*Assumptions!B5 -> 543.44576 | G7: =E7*F7 -> 543.44576 | H7: Formula: pack price × rate × import ÷ 100 × circles per sleeve | I7: Cytiva/Whatman via Indian lab distributors (Biomall, Chemopharm)
A8: 7 | B8: Mesh wrap, 50 µm | C8: 316L 300-mesh twill, 1 sq ft (uses 0.037 m²) | D8: Buy | E8: 1 | F8: 1000 | G8: =E8*F8 -> 1000 | H8: Estimate; IndiaMART 316 filter cloth lists ₹50–450/sq ft | I8: Banaraswala Wire Mesh; Ambani Metals; Satish Wire
A9: 8 | B9: Basket with welded vanes | C9: 316L perforated 0.6 mm Ø2/3.1 mm hex, 300 × 300 piece + 316 floor/hub + 4 vanes; roll, seam and TIG | D9: Make | E9: 1 | F9: 4200 | G9: =E9*F9 -> 4200 | H9: Estimate: sheet ₹1,500 + CNC ₹800 + laser ₹400 + welding ₹1,500 | I9: Perforated sheet: Adarsh Metal Perforators, Excel Metal (Mumbai); welding: Peenya
A10: 9 | B10: Sleeve floor gasket | C10: Silicone sheet 300 × 300 × 1.5, food grade; cut rings | D10: Buy | E10: 1 | F10: 350 | G10: =E10*F10 -> 350 | H10: Estimate | I10: IndiaMART silicone sheet suppliers
A11: 10 | B11: Drive coupler | C11: 316 Ø18 × 6, Ø5 bore, M3 grub | D11: Make | E11: 1 | F11: 700 | G11: =E11*F11 -> 700 | H11: Estimate, CNC one-off; 316 bar ≈ ₹240/kg | I11: CNC job shops, Peenya
A12: 11 | B12: Shaft lip seal | C12: FKM 5 × 12 × 4 | D12: Buy | E12: 1 | F12: 250 | G12: =E12*F12 -> 250 | H12: Estimate | I12: Seal stockists (Moglix, local bearing shops)
A13: 12 | B13: Base housing | C13: PETG print ≈ 250 g, 0.6 mm walls | D13: Make | E13: 1 | F13: 1500 | G13: =E13*F13 -> 1500 | H13: Estimate, Bangalore print services ≈ ₹5–7/g | I13: Local FDM print services
A14: 13 | B14: Feet ×4 | C14: Silicone bumpers Ø14 | D14: Buy | E14: 1 | F14: 120 | G14: =E14*F14 -> 120 | H14: Estimate | I14: Hardware stores
A15: 14 | B15: Motor 42BLS02 | C15: 24 V, 4,000 rpm, 0.125 N·m, 52.5 W, 61 mm; confirm hall leads | D15: Buy | E15: 1 | F15: 2080 | G15: =E15*F15 -> 2080 | H15: robu.in listing, Oct 2026 | I15: Robu.in; Aerokart; Robodo (JK42BLS04, ₹3,200, if more torque is needed)
A16: 15 | B16: Controller | C16: ESP32 DevKit V1 ₹405 + ZS-X11H 6–60 V hall BLDC driver ₹1,299 + knob, LED, toggle, perfboard ₹400 | D16: Buy | E16: 1 | F16: 2104 | G16: =E16*F16 -> 2104 | H16: techiesms.com + probots.co.in listings + estimate | I16: Probots; Techiesms; Robocraze
A17: 16 | B17: 24 V 5 A supply | C17: SMPS 100–240 V in, 24 V 5 A out, plus DC jack and cable | D17: Buy | E17: 1 | F17: 807 | G17: =E17*F17 -> 807 | H17: robocraze.com listing ₹707 + ₹100 cable | I17: Robocraze; Probots (Mean Well LRS series)
A18: 17 | B18: Fasteners | C18: A4 stainless M3/M4 screws, grub screws | D18: Buy | E18: 1 | F18: 300 | G18: =E18*F18 -> 300 | H18: Estimate | I18: Local
A19: 18 | B19: Electropolish + passivation | C19: All 304/316 wet parts, ASTM A967 | D19: Buy | E19: 1 | F19: 1500 | G19: =E19*F19 -> 1500 | H19: Estimate per lot | I19: SS finishing shops, Peenya
B21: Prototype kit, all lines (₹) | G21: =SUM(G2:G19) -> 22334.446
B22: Kits to build | G22: =Assumptions!B6 -> 2
B23: Prototype hardware budget (₹) | G23: =G21*G22 -> 44668.892
B24: Sleeve stock: one pack of 100 circles = 25 sleeves (₹) | G24: =Assumptions!B4*Assumptions!B2*(1+Assumptions!B3) -> 13586.144
B25: Total with sleeve stock (₹) | G25: =G23+G24 -> 58255.036
B26: PD-298 prototyping cap (₹) | G26: =Assumptions!B7 -> 50000
B27: Within cap? | G27: =IF(G25<=G26,"yes","no") -> no
B29: Blue on yellow: estimate or choice to replace with an RFQ quote. Green: pulled from the Assumptions tab. Black: formula.

Sheet Teardown
A1: Item | B1: Part | C1: Function | D1: Material | E1: Process | F1: Mass g (drawn) | G1: Mates with | H1: Change in v1.1 (TRIZ / FMEA ref.)
A2: 1 | B2: Lid with fill chute and window | C2: Closes the bowl; Ø16 chute and funnel dose the batch; glass window to watch the drain | D2: 304, 1.2 mm; borosilicate window | E2: Spin/press lid, roll + TIG chute, TIG funnel | F2: 474.6 | G2: 3 bowl rim; 2 interlock tab | H2: Lid held locked while the basket turns (FMEA 15)
A3: 2 | B3: Lid interlock + lock | C3: Reed switch proves the lid is shut; solenoid pin holds it until speed = 0 | D3: Bought: reed switch, magnet, 24 V mini solenoid | E3: Buy; mount on base deck | F3: 25 | G3: 1 lid tab; 15 controller | H3: Lock added (FMEA 15, PC4)
A4: 3 | B4: Bowl, spout and flow pins | C4: Catches the water off the cage; spout to the jug; two pins sense water in the spout | D4: 304, 1.0 mm (drawn), 0.6–0.8 mm in prototype | E4: Roll + seam weld, weld floor and boss, roll rim; tube spout; 316 pins | F4: 1310.6 | G4: 12 base; 11 seal in the boss; 1 lid | H4: Flow pins added: batch-end and end-of-life signal (principle 23 Feedback; FMEA 10, 12, 14; req. 4.2)
A5: 4 | B5: Sleeve clamp ring | C5: Clamps the sleeve top onto the cage rim | D5: 316 | E5: CNC turn, knurl | F5: 39.3 | G5: 8 basket; 5 O-ring; 6 sleeve | H5: —
A6: 5 | B6: Sleeve O-ring | C6: Seals the sleeve top edge | D6: Silicone 60 ShA, food grade | E6: Buy | F6: 0.4 | G6: 4 ring; 6 sleeve | H6: —
A7: 6 | B7: Filter sleeve, two layers | C7: The filter and the sample; inner layer catches most, outer layer catches what passes and covers inner seams | D7: Cellulose, Grade 602 h class, 2 layers | E7: Cut 4 strips from 240 mm circles; 20 mm overlaps, seams 90° apart | F7: 6 | G7: 8 cage (via 7 mesh); 9 gasket; 5 O-ring | H7: Second layer (TC1, PC1); 20 mm overlaps pressed shut by the spin (principle 25)
A8: 7 | B8: Mesh wrap, 50 µm | C8: Holds the wet paper over the Ø2 holes | D8: 316L 300-mesh twill | E8: Cut, wrap, spot-weld seam | F8: 9.1 | G8: 8 cage | H8: —
A9: 8 | B9: Basket with welded vanes | C9: Spins the batch; vanes drag the water to ≈ 85 % of basket speed | D9: 316L perforated 0.6 mm, Ø2 at 40 % open; 4 vanes 1 mm; floor + hub | E9: Laser cut, roll + seam weld, TIG vanes to floor and tie ring | F9: 245.2 | G9: 10 coupler; 6 sleeve; 4 ring | H9: Vanes welded in: one part fewer to remove (TC3, principle 10; FMEA 9, 17); vane tips at r 28 leave room to slide the sleeve in
A10: 9 | B10: Sleeve floor gasket | C10: Seals the sleeve's bottom edge to the floor | D10: Silicone sheet 1.5 mm, food grade | E10: Die/knife cut | F10: 0.6 | G10: 8 basket floor; 6 sleeve | H10: New: closes the bottom bypass (FMEA 2)
A11: 10 | B11: Drive coupler | C11: Joins the basket to the Ø5 motor shaft | D11: 316 | E11: CNC turn, M3 grub screw | F11: 11.2 | G11: 14 shaft; 8 basket | H11: —
A12: 11 | B12: Shaft lip seal | C12: Keeps water out of the dry base | D12: FKM, 5 × 12 × 4 | E12: Buy | F12: 0.6 | G12: 3 bowl boss; 14 shaft | H12: Boss raised 14 mm above the floor; drip path (FMEA 7)
A13: 12 | B13: Base housing | C13: Holds motor, controller, controls; dry side | D13: PETG (prototype) / PC-ABS (product) | E13: FDM print / injection mould | F13: 205.5 | G13: 3 bowl; 13 feet; 14, 15 | H13: —
... A17: 16 | B17: 24 V 5 A supply | C17: Power | D17: Bought SMPS | E17: Buy | F17: 0 | G17: 15 controller | H17: External; not drawn
B19: Total mass as drawn (g) | F19: =SUM(F2:F17) -> 2836.1
B20: Spinning mass: items 4–10 (g) | F20: =SUM(F5:F11) -> 311.8
B22: Masses from the teardown geometry (Pappus volumes × density). The drawn bowl and lid are 1.0–1.2 mm; at 0.6–0.8 mm the unit is about 0.6 kg lighter.

Sheet Assumptions
A1: Assumption | B1: Value | C1: Unit | D1: Source / note
A2: USD → INR exchange rate | B2: 88 | C2: ₹/$ | D2: Assumed for Oct 2026; edit to the day's rate
A3: Import, shipping and duty on imported lab paper | B3: 0.3 | C3: fraction | D3: Assumed; Indian lab distributors quote landed prices on login
A4: Grade 602 h, 240 mm circles, pack of 100 | B4: 118.76 | C4: $/pack | D4: scientificfilters.com list (cat. 10312620), Oct 2026
A5: 602 h circles per two-layer sleeve | B5: 4 | C5: circles | D5: A 240 mm circle yields a 158 × 180 mm strip; 2 strips per layer, 2 layers
A6: Prototype kits to build | B6: 2 | C6: kits | D6: One to test, one to break
A7: PD-298 prototyping cap | B7: 50000 | C7: ₹ | D7: Department cap used for earlier MPx concepts; edit if different
A8: Sleeve life, tap water (simulated) | B8: 228 | C8: L | D8: v11.mjs: litres until the batch cycle falls below 15 L/h; cake resistance assumed
A9: Sleeve life, borewell (simulated) | B9: 57 | C9: L | D9: same model, 2 mg/L solids
A10: Sleeve life, turbid surface (simulated) | B10: 11.4 | C10: L | D10: same model, 10 mg/L solids
A12: Blue text on yellow = input you can edit; every other number in the workbook is a formula or comes from the drawings.

Sheet Running cost
A1: Water | B1: Sleeve life (L, simulated) | C1: Sleeve cost ₹ | D1: Cost per litre ₹ | E1: Sleeves per year at 3 L/day | F1: Sleeve cost per year ₹
A2: Tap | B2: =Assumptions!B8 -> 228 | C2: =BOM!F7 -> 543.44576 | D2: =IF(B2>0,C2/B2,0) -> 2.383534 | E2: =IF(B2>0,3*365/B2,0) -> 4.8026316 | F2: =E2*C2 -> 2609.9698
A3: Borewell | B3: =Assumptions!B9 -> 57 | C3: =BOM!F7 -> 543.44576 | D3: =IF(B3>0,C3/B3,0) -> 9.5341361 | E3: =IF(B3>0,3*365/B3,0) -> 19.210526 | F3: =E3*C3 -> 10439.879
A4: Turbid surface | B4: =Assumptions!B10 -> 11.4 | C4: =BOM!F7 -> 543.44576 | D4: =IF(B4>0,C4/B4,0) -> 47.670681 | E4: =IF(B4>0,3*365/B4,0) -> 96.052632 | F4: =E4*C4 -> 52199.395
A6: Sleeve life = litres until the batch cycle falls below 15 L/h (cake on the sleeve, α = 10¹³ m/kg assumed). Bench test 4 replaces it.

Sheet Suppliers
A1: Item | B1: Supplier / listing | C1: Location | D1: What they list | E1: Ask in the RFQ | F1: Source
A2: 14 | B2: Robu.in — 42BLS02 | C2: Pune (online) | D2: 24 V BLDC 4,000 rpm, 0.125 N·m, 52.5 W, 61 mm, 430 g, ₹2,080 | E2: Confirm hall-sensor leads and 5 mm shaft | F2: https://st.robu.in/product/42bls02-24v-rpm4000-0-125-n-cm-61mm
A3: 14 alt | B3: Robodo — JK42BLS04 | C3: online | D3: 24 V, 4,000 rpm, 0.25 N·m, 105 W, Ø5 shaft, hall sensors, 100 mm, ₹3,200 | E3: If spin-up torque is short | F3: https://robodo.in/products/jk42bls04-brushless-motor-105-watt-bldc
A4: 15 | B4: Probots — ZS-X11H | C4: Bangalore (online) | D4: 6–60 V, 400 W hall BLDC driver, PWM / 0–5 V speed input, ₹1,299 | E4: Speed-pulse output for closed loop | F4: https://probots.co.in/zs-x11h-400w-bldc-3-phase-brushless-motor-controller-6v-60v-pwm-hall-driver-module.html
A5: 15 | B5: Techiesms — ESP32 DevKit V1 | C5: online | D5: ESP32-WROOM-32 board, ₹405 | E5: — | F5: https://techiesms.com/product/esp32-development-board-doit-devkit-v1/
A6: 16 | B6: Robocraze — 24 V 5 A SMPS | C6: Bangalore (online) | D6: 100–240 V in, 24 V 5 A, IP20 metal case, ₹707 | E6: Enclosed desktop adapter for the product | F6: https://robocraze.com/products/24v-5a-smps-power-supply
A7: 2 | B7: Robocraze — 12 mm reed switch | C7: online | D7: NO reed, 1.2 A, 24 V DC, ₹28 | E7: Pair with a 24 V mini solenoid for the lock | F7: https://robocraze.com/products/12mm-reed-switch
A8: 6 | B8: Whatman 602 h circles | C8: Cytiva via distributors | D8: 602 h, 100 per pack: 125 mm $37.93, 150 mm $55.06, 185 mm $80.87, 240 mm $134.29 list ($118.76 sale) | E8: Ask Cytiva India for 602 h in sheets or rolls (no 602 h sheets were found listed) | F8: https://scientificfilters.com/whatman/6-602h
A9: 6 alt | B9: Whatman Grade 42, 46 × 57 cm sheets | C9: Chemopharm (India) | D9: Cat. 1442-917, 100 sheets; 8–12 weeks | E9: Slower and coarser (2.5 µm) than 602 h; fallback only | F9: https://store.chemopharm.com/no-42-filter-sheets-46x57cm-100-wh-ma-bo-1442917
A10: 7 | B10: IndiaMART filter wire cloth | C10: Coimbatore / Mumbai | D10: 316 filter cloth ₹50–450 per sq ft (Banaraswala 400-mesh ₹50/sq ft; Ambani Metals 150-mesh twill ₹450/sq ft) | E10: 300-mesh 316L twill, 1 sq ft, mill certificate | F10: https://m.indiamart.com/impcat/filter-wire-cloth.html
A11: 8 | B11: Perforated sheet (L&T SuFin listings) | C11: Mumbai | D11: SS 316 perforated sheets 1,250 × 2,500 (Adarsh Metal Perforators) | E11: 0.6 mm 316L, Ø2 holes, 3.1 mm 60° pitch, 300 × 300 cut piece | F11: https://lntsufin.com/product/adarsh-metal-perforators-2-mm-stainless-steel-perforated-sheet-for-screening-and-fencing-1250-x-2500-mm-ss-316-astm-a240/16120-466
A12: 4, 8, 10 | B12: SS 316 round bar | C12: Raigad (L&T SuFin) | D12: Category RFQ prices ₹226–250/kg (Jul–Sep 2026) | E12: Ø20 and Ø70 offcuts | F12: https://lntsufin.com/product/sps-ss-316-20-mm-stainless-steel-round-bars-6-m/17330-457
A13: — | B13: Carson MicroFlip MP-250 (already owned) | C13: Tanotis (India) | D13: 100–250× pocket microscope, ₹3,390 incl. GST and import | E13: Spare unit for the second kit | F13: https://tanotis.com/products/carson-microflip-mp-250-100-250x-pocket-microscope

Sheet FMEA
A1: # | B1: Part / function | C1: Failure mode | D1: Effect on user | E1: Cause | F1: Control (v1) | G1: O | H1: S | I1: D | J1: RN | K1: Critical? | L1: Action in v1.1 | M1: O new | N1: S new | O1: D new | P1: RN new | Q1: Critical? | R1: Req. | S1: New in v1.1
A2: 1 | B2: Sleeve paper | C2: Capture falls at high face velocity | D2: 1–2 µm particles pass | E2: Rated at 1/7 of the working velocity | F2: None | G2: 6 | H2: 9 | I2: 9 | J2: =G2*H2*I2 -> 486 | K2: =IF(J2>125,"critical","") -> critical | L2: Speed profile ≤ 5× face velocity; second layer; bead test 5 | M2: 2 | N2: 9 | O2: 6 | P2: =M2*N2*O2 -> 108 | Q2: =IF(P2>125,"critical","") | R2: 6.1
A3: 2 | B3: Sleeve seam and ends | C3: Water bypasses the paper | D3: Unfiltered particles reach the jug | E3: Seam or ends unsealed (rig K 3.2× datasheet) | F3: Clamp ring + O-ring | G3: 6 | H3: 9 | I3: 8 | J3: =G3*H3*I3 -> 432 | K3: =IF(J3>125,"critical","") -> critical | L3: 20 mm overlaps pressed by spin; seams 90° apart in 2 layers; floor gasket; dye test | M3: 2 | N3: 9 | O3: 5 | P3: =M3*N3*O3 -> 90 | Q3: =IF(P3>125,"critical","") | R3: 6.1
A4: 3 | B4: Detection | C4: Cellulose fibres or stain read as plastic | D4: False positives | E4: Nile red uptake by cellulose | F4: None | G4: 8 | H4: 7 | I4: 7 | J4: =G4*H4*I4 -> 392 | K4: =IF(J4>125,"critical","") -> critical | L4: Blank sleeve per batch of sleeves; fibre-shape exclusion; reference counts | M4: 4 | N4: 7 | O4: 4 | P4: =M4*N4*O4 -> 112 | Q4: =IF(P4>125,"critical","") | R4: 6.2
A5: 4 | B5: Spent sleeve | C5: Binned loose or rinsed | D5: Microplastics back to the environment | E5: No disposal route | F5: None | G5: 7 | H5: 6 | I5: 8 | J5: =G5*H5*I5 -> 336 | K5: =IF(J5>125,"critical","") -> critical | L5: Sealed sleeve pouch in the box; return-to-lab route for the study | M5: 3 | N5: 6 | O5: 6 | P5: =M5*N5*O5 -> 108 | Q5: =IF(P5>125,"critical","") | R5: 10.1
A6: 5 | B6: Light polymers | C6: PP / PE miss the paper or land unevenly | D6: Sample under-counts them | E6: Inward drift beats through-flow above ≈ 20 µm | F6: None | G6: 6 | H6: 6 | I6: 8 | J6: =G6*H6*I6 -> 288 | K6: =IF(J6>125,"critical","") -> critical | L6: Slow stop; floor coupon counted; PP bead test | M6: 4 | N6: 6 | O6: 5 | P6: =M6*N6*O6 -> 120 | Q6: =IF(P6>125,"critical","") | R6: 1.2
A7: 6 | B7: Speed control | C7: Speed drifts out of the band | D7: Low flow or uncertain capture | E7: Open-loop PWM, no feedback | F7: None | G7: 6 | H7: 6 | I7: 8 | J7: =G7*H7*I7 -> 288 | K7: =IF(J7>125,"critical","") -> critical | L7: Hall-sensor closed loop on the ESP32; speed logged | M7: 2 | N7: 6 | O7: 2 | P7: =M7*N7*O7 -> 24 | Q7: =IF(P7>125,"critical","") | R7: 2.1
A8: 7 | B8: Lip seal | C8: Leaks into the dry base | D8: Water on the motor and board | E8: Wear at speed, dry running | F8: Lip seal | G8: 4 | H8: 7 | I8: 7 | J8: =G8*H8*I8 -> 196 | K8: =IF(J8>125,"critical","") -> critical | L8: Boss 14 mm above the floor; drip path out of the base; board on stand-offs | M8: 3 | N8: 5 | O8: 4 | P8: =M8*N8*O8 -> 60 | Q8: =IF(P8>125,"critical","") | R8: 3.5
A9: 8 | B9: Wet sleeve | C9: Tears or creases at 55–150 g | D9: Bypass; fibres in the water | E9: Wet strength over Ø2 holes | F9: Mesh support | G9: 4 | H9: 8 | I9: 6 | J9: =G9*H9*I9 -> 192 | K9: =IF(J9>125,"critical","") -> critical | L9: Two layers; inspect on lift-out; 20-batch test 7 | M9: 3 | N9: 8 | O9: 4 | P9: =M9*N9*O9 -> 96 | Q9: =IF(P9>125,"critical","") | R9: 6.1
A10: 9 | B10: Sleeve change | C10: Sample touched or dropped | D10: Contaminated sample, spilled catch | E10: Four-step removal, wet hands | F10: None | G10: 5 | H10: 6 | I10: 6 | J10: =G10*H10*I10 -> 180 | K10: =IF(J10>125,"critical","") -> critical | L10: Three steps (vanes welded in); tweezer tabs; gloves; pouch | M10: 3 | N10: 6 | O10: 4 | P10: =M10*N10*O10 -> 72 | Q10: =IF(P10>125,"critical","") | R10: 10.2
A11: 10 | B11: Speed profile | C11: Starts fast with a full basket | D11: Face velocity ≈ 20× at the start | E11: Firmware fault or wrong batch size | F11: — (new in v1.1) | G11: 3 | H11: 7 | I11: 7 | J11: =G11*H11*I11 -> 147 | K11: =IF(J11>125,"critical","") -> critical | L11: Start capped at 1,300 rpm until the flow pins see water; batch size fixed by the funnel | M11: 2 | N11: 7 | O11: 4 | P11: =M11*N11*O11 -> 56 | Q11: =IF(P11>125,"critical","") | R11: 6.1 | S11: yes
A12: 11 | B12: Detection | C12: Too few particles per field | D12: Count meaningless | E12: Sparse sample on a large sleeve | F12: None | G12: 9 | H12: 6 | I12: 2 | J12: =G12*H12*I12 -> 108 | K12: =IF(J12>125,"critical","") | L12: Coupons after ≥ 20 L on one sleeve | M12: 4 | N12: 6 | O12: 2 | P12: =M12*N12*O12 -> 48 | Q12: =IF(P12>125,"critical","") | R12: 6.2
A13: 12 | B13: Silt | C13: Sleeve blinds early | D13: Flow under 15 L/h | E13: Borewell / turbid water | F13: None | G13: 7 | H13: 5 | I13: 3 | J13: =G13*H13*I13 -> 105 | K13: =IF(J13>125,"critical","") | L13: Life 228 / 57 / 11 L; alert from drain time | M13: 4 | N13: 5 | O13: 2 | P13: =M13*N13*O13 -> 40 | Q13: =IF(P13>125,"critical","") | R13: 9.1
A14: 13 | B14: Cellulose sleeve | C14: Sheds fibres into the water | D14: Particles in the output | E14: Paper rubbing on the mesh | F14: None | G14: 5 | H14: 3 | I14: 7 | J14: =G14*H14*I14 -> 105 | K14: =IF(J14>125,"critical","") | L14: 200 mL first flush to waste | M14: 3 | N14: 3 | O14: 5 | P14: =M14*N14*O14 -> 45 | Q14: =IF(P14>125,"critical","") | R14: 3.2
A15: 14 | B15: Flow pins | C15: Pins foul with lime | D15: Wrong batch-end signal | E15: Scale on 316 pins | F15: — (new in v1.1) | G15: 5 | H15: 4 | I15: 5 | J15: =G15*H15*I15 -> 100 | K15: =IF(J15>125,"critical","") | L15: Pins wiped at each sleeve change; timed fallback profile | M15: 3 | N15: 4 | O15: 4 | P15: =M15*N15*O15 -> 48 | Q15: =IF(P15>125,"critical","") | R15: 4.2 | S15: yes
A16: 15 | B16: Lid | C16: Opened while spinning | D16: Hand near a basket at 7.9 m/s | E16: Interlock bypassed | F16: Reed switch | G16: 3 | H16: 8 | I16: 4 | J16: =G16*H16*I16 -> 96 | K16: =IF(J16>125,"critical","") | L16: Solenoid lock until hall speed = 0 | M16: 2 | N16: 8 | O16: 2 | P16: =M16*N16*O16 -> 32 | Q16: =IF(P16>125,"critical","") | R16: safety
A17: 16 | B17: Cost | C17: Price over ₹6,000 | D17: Not affordable | E17: Steel parts, BLDC drive | F17: None | G17: 8 | H17: 6 | I17: 2 | J17: =G17*H17*I17 -> 96 | K17: =IF(J17>125,"critical","") | L17: Rolled parts, printed base; production costing next | M17: 6 | N17: 6 | O17: 2 | P17: =M17*N17*O17 -> 72 | Q17: =IF(P17>125,"critical","") | R17: 11.1
A18: 17 | B18: Vanes | C18: Water lags (< 50 % of basket) | D18: Flow under 15 L/h | E18: Too few or short vanes | F18: 4-vane insert | G18: 5 | H18: 6 | I18: 3 | J18: =G18*H18*I18 -> 90 | K18: =IF(J18>125,"critical","") | L18: Welded vanes; bench test 1; profile adapts to drain time | M18: 3 | N18: 6 | O18: 2 | P18: =M18*N18*O18 -> 36 | Q18: =IF(P18>125,"critical","") | R18: 2.1
A19: 18 | B19: Basket | C19: Unbalance from an uneven wet sleeve | D19: Vibration, noise | E19: Uneven cake or sleeve | F19: None | G19: 6 | H19: 4 | I19: 2 | J19: =G19*H19*I19 -> 48 | K19: =IF(J19>125,"critical","") | L19: Pre-spin seats the sleeve; feet; 5 g → 10 N at 2,500 rpm checked | M19: 4 | N19: 5 | O19: 2 | P19: =M19*N19*O19 -> 40 | Q19: =IF(P19>125,"critical","") | R19: 8.1
A20: 19 | B20: Motor / driver | C20: Stalls or overheats | D20: No flow | E20: Start torque, no current limit | F20: None | G20: 3 | H20: 5 | I20: 3 | J20: =G20*H20*I20 -> 45 | K20: =IF(J20>125,"critical","") | L20: Soft start; driver current limit | M20: 2 | N20: 5 | O20: 3 | P20: =M20*N20*O20 -> 30 | Q20: =IF(P20>125,"critical","") | R20: 2.1
A21: 20 | B21: Bowl | C21: Spray over the rim | D21: Wet bench | E21: Water leaves the cage at ≈ 7 m/s | F21: Skirt | G21: 5 | H21: 3 | I21: 2 | J21: =G21*H21*I21 -> 30 | K21: =IF(J21>125,"critical","") | L21: Skirt kept; lid closes the rim | M21: 3 | N21: 3 | O21: 2 | P21: =M21*N21*O21 -> 18 | Q21: =IF(P21>125,"critical","") | R21: —
B23: Critical modes | J23: =COUNTIF(J2:J21,">125") -> 10 | P23: =COUNTIF(P2:P21,">125") -> 0
B24: Sum of RN | J24: =SUM(J2:J21) -> 3760 | P24: =SUM(P2:P21) -> 1255
B26: O, S, D 1–10 (Pahl & Beitz §10.4). Draft ratings in blue on yellow: change them in the team session and RN and the counts update.

Sheet TRIZ
A1: ID | B1: Contradiction | C1: Improving parameter | D1: Worsening parameter | E1: Matrix principles | F1: Principle used | G1: Idea | H1: Verdict
A2: TC1 | B2: Capture vs flow | C2: #30 Object-affected harmful factors | D2: #39 Productivity | E2: 22, 35, 13, 24 | F2: 24 Intermediary | G2: a second sleeve layer catches what the first misses and covers its seams | H2: adopted
A3: TC1 | B3: Capture vs flow | C3: #30 Object-affected harmful factors | D3: #39 Productivity | E3: 22, 35, 13, 24 | F3: 10 Preliminary action | G3: flush a new sleeve with 200 mL to waste before use | H3: adopted
A4: TC1 | B4: Capture vs flow | C4: #30 Object-affected harmful factors | D4: #39 Productivity | E4: 22, 35, 13, 24 | F4: 22 Blessing in disguise | G4: silt cake as an extra depth filter | H4: not relied on
A5: TC1 | B5: Capture vs flow | C5: #30 Object-affected harmful factors | D5: #39 Productivity | E5: 22, 35, 13, 24 | F5: 13 The other way round | G5: make particles bigger with a coagulant | H5: rejected: adds a chemical
A6: TC2 | B6: Speed vs capture certainty | C6: #39 Productivity | D6: #27 Reliability · #31 harmful side effects | E6: 1, 35, 10, 38 · 35, 22, 18, 39 | F6: 35 Parameter changes | G6: speed profile: slow while the basket is full, faster as it drains, face velocity held at 5× | H6: adopted
A7: TC2 | B7: Speed vs capture certainty | C7: #39 Productivity | D7: #27 Reliability · #31 harmful side effects | E7: 1, 35, 10, 38 · 35, 22, 18, 39 | F7: 10 Preliminary action | G7: 300 rpm pre-spin seats the sleeve and the water before the ramp | H7: adopted
A8: TC2 | B8: Speed vs capture certainty | C8: #39 Productivity | D8: #27 Reliability · #31 harmful side effects | E8: 1, 35, 10, 38 · 35, 22, 18, 39 | F8: 1 Segmentation | G8: split the batch into small doses | H8: rejected: pour already 10 s
A9: TC2 | B9: Speed vs capture certainty | C9: #39 Productivity | D9: #27 Reliability · #31 harmful side effects | E9: 1, 35, 10, 38 · 35, 22, 18, 39 | F9: 18 Mechanical vibration | G9: silicone feet isolate the residual unbalance | H9: kept
A10: TC3 | B10: Water speed vs simplicity | C10: #9 Speed | D10: #33 Ease of operation · #36 Device complexity | E10: 32, 28, 13, 12 · 10, 28, 4, 34 | F10: 10 Preliminary action | G10: vanes welded into the basket; the sleeve slides past their tips | H10: adopted
A11: TC3 | B11: Water speed vs simplicity | C11: #9 Speed | D11: #33 Ease of operation · #36 Device complexity | E11: 32, 28, 13, 12 · 10, 28, 4, 34 | F11: 13 · 34 | G11: pleats in the sleeve act as the vanes and are thrown away with it | H11: rejected by simulation
A12: TC3 | B12: Water speed vs simplicity | C12: #9 Speed | D12: #33 Ease of operation · #36 Device complexity | E12: 32, 28, 13, 12 · 10, 28, 4, 34 | F12: 28 Mechanics substitution | G12: tangential jet spins the water up | H12: rejected: pour energy too small
... A21: TC6 | B21: Plastic-free wet path vs complexity | C21: #31 Object-generated harmful factors | D21: #36 Device complexity | E21: 19, 1, 31 | F21: 31 Porous materials | G21: perforated cage + woven mesh stay steel | H21: kept
A23: ID | B23: Physical contradiction | C23: Separation | D23: Resolution in v1.1
A24: PC1 | B24: Pores must be small (catch 1 µm) and large (pass 15 L/h) | C24: Space | D24: two layers in series: each stays as open as 602 h, together they catch 98.9 % at 1–2 µm
A25: PC2 | B25: The basket must spin fast (flow) and slowly (paper rating, noise) | C25: Time | D25: speed profile: about 1,250 rpm when full, rising to 2,500 rpm as the water thins
A26: PC3 | B26: Particles must reach the paper and float inward (PP, PE > 20 µm) | C26: Condition | D26: slow, steady stop lets the floating layer settle onto the sleeve; count a floor coupon too
A27: PC4 | B27: The sleeve must be sealed and removable | C27: Time + self-service (25) | D27: spin pressure presses the 20 mm overlaps shut; floor gasket and clamp ring seal the ends; lifts out when stopped
A29: Matrix cells from the TRIZ40 contradiction matrix (triz40.com/aff_Matrix_TRIZ.php), checked cell by cell.
